fancy_nlp/__init__.py
fancy_nlp/config.py
fancy_nlp/applications/__init__.py
fancy_nlp/applications/ner.py
fancy_nlp/applications/spm.py
fancy_nlp/applications/text_classification.py
fancy_nlp/callbacks/__init__.py
fancy_nlp/callbacks/ensemble.py
fancy_nlp/callbacks/metrics.py
fancy_nlp/layers/__init__.py
fancy_nlp/layers/attention.py
fancy_nlp/layers/crf.py
fancy_nlp/layers/matching.py
fancy_nlp/layers/other.py
fancy_nlp/losses/__init__.py
fancy_nlp/losses/crf_losses.py
fancy_nlp/metrics/__init__.py
fancy_nlp/metrics/crf_accuracies.py
fancy_nlp/models/__init__.py
fancy_nlp/models/base_model.py
fancy_nlp/models/ner/__init__.py
fancy_nlp/models/ner/base_ner_model.py
fancy_nlp/models/ner/ner_models.py
fancy_nlp/models/spm/__init__.py
fancy_nlp/models/spm/base_spm_model.py
fancy_nlp/models/spm/spm_models.py
fancy_nlp/models/text_classification/__init__.py
fancy_nlp/models/text_classification/base_text_classification_model.py
fancy_nlp/models/text_classification/text_classification_models.py
fancy_nlp/predictors/__init__.py
fancy_nlp/predictors/ner_predictor.py
fancy_nlp/predictors/spm_predictor.py
fancy_nlp/predictors/text_classification_predictor.py
fancy_nlp/preprocessors/__init__.py
fancy_nlp/preprocessors/ner_preprocessor.py
fancy_nlp/preprocessors/preprocessor.py
fancy_nlp/preprocessors/spm_preprocessor.py
fancy_nlp/preprocessors/text_classification_preprocessor.py
fancy_nlp/trainers/__init__.py
fancy_nlp/trainers/ner_trainer.py
fancy_nlp/trainers/spm_trainer.py
fancy_nlp/trainers/text_classification_trainer.py
fancy_nlp/utils/__init__.py
fancy_nlp/utils/data_generator.py
fancy_nlp/utils/data_loader.py
fancy_nlp/utils/embedding.py
fancy_nlp/utils/other.py
fancy_nlp/utils/save_load_model.py
fancy_nlp-1.0.0.dist-info/LICENSE
fancy_nlp-1.0.0.dist-info/METADATA
fancy_nlp-1.0.0.dist-info/WHEEL
fancy_nlp-1.0.0.dist-info/top_level.txt
fancy_nlp-1.0.0.dist-info/RECORD
